mezzanine/__init__.py
mezzanine/urls.py
mezzanine/accounts/__init__.py
mezzanine/accounts/admin.py
mezzanine/accounts/defaults.py
mezzanine/accounts/forms.py
mezzanine/accounts/models.py
mezzanine/accounts/urls.py
mezzanine/accounts/views.py
mezzanine/accounts/locale/ar/LC_MESSAGES/django.mo
mezzanine/accounts/locale/ar/LC_MESSAGES/django.po
mezzanine/accounts/locale/bg/LC_MESSAGES/django.mo
mezzanine/accounts/locale/bg/LC_MESSAGES/django.po
mezzanine/accounts/locale/ca/LC_MESSAGES/django.mo
mezzanine/accounts/locale/ca/LC_MESSAGES/django.po
mezzanine/accounts/locale/cs/LC_MESSAGES/django.mo
mezzanine/accounts/locale/cs/LC_MESSAGES/django.po
mezzanine/accounts/locale/da/LC_MESSAGES/django.mo
mezzanine/accounts/locale/da/LC_MESSAGES/django.po
mezzanine/accounts/locale/de/LC_MESSAGES/django.mo
mezzanine/accounts/locale/de/LC_MESSAGES/django.po
mezzanine/accounts/locale/en/LC_MESSAGES/django.mo
mezzanine/accounts/locale/en/LC_MESSAGES/django.po
mezzanine/accounts/locale/eo/LC_MESSAGES/django.mo
mezzanine/accounts/locale/eo/LC_MESSAGES/django.po
mezzanine/accounts/locale/es/LC_MESSAGES/django.mo
mezzanine/accounts/locale/es/LC_MESSAGES/django.po
mezzanine/accounts/locale/et/LC_MESSAGES/django.mo
mezzanine/accounts/locale/et/LC_MESSAGES/django.po
mezzanine/accounts/locale/fa/LC_MESSAGES/django.mo
mezzanine/accounts/locale/fa/LC_MESSAGES/django.po
mezzanine/accounts/locale/fa_IR/LC_MESSAGES/django.mo
mezzanine/accounts/locale/fa_IR/LC_MESSAGES/django.po
mezzanine/accounts/locale/fi/LC_MESSAGES/django.mo
mezzanine/accounts/locale/fi/LC_MESSAGES/django.po
mezzanine/accounts/locale/fr/LC_MESSAGES/django.mo
mezzanine/accounts/locale/fr/LC_MESSAGES/django.po
mezzanine/accounts/locale/hr_HR/LC_MESSAGES/django.mo
mezzanine/accounts/locale/hr_HR/LC_MESSAGES/django.po
mezzanine/accounts/locale/hu/LC_MESSAGES/django.mo
mezzanine/accounts/locale/hu/LC_MESSAGES/django.po
mezzanine/accounts/locale/id_ID/LC_MESSAGES/django.mo
mezzanine/accounts/locale/id_ID/LC_MESSAGES/django.po
mezzanine-6.1.1.dist-info/licenses/LICENSE
mezzanine-6.1.1.dist-info/METADATA
mezzanine-6.1.1.dist-info/WHEEL
mezzanine-6.1.1.dist-info/entry_points.txt
mezzanine-6.1.1.dist-info/top_level.txt
mezzanine-6.1.1.dist-info/RECORD
