Metadata-Version: 2.4
Name: Mezzanine
Version: 6.1.1
Summary: An open source content management platform built using the Django framework.
Home-page: http://mezzanine.jupo.org/
Author: Stephen McDonald
Author-email: stephen.mc@gmail.com
License: BSD
Classifier: Development Status :: 5 - Production/Stable
Classifier: Environment :: Web Environment
Classifier: Framework :: Django
Classifier: Intended Audience :: Developers
Classifier: License :: OSI Approved :: BSD License
Classifier: Operating System :: OS Independent
Classifier: Programming Language :: Python
Classifier: Programming Language :: Python :: 3
Classifier: Programming Language :: Python :: 3.8
Classifier: Programming Language :: Python :: 3.9
Classifier: Programming Language :: Python :: 3.10
Classifier: Programming Language :: Python :: 3.11
Classifier: Programming Language :: Python :: 3.12
Classifier: Framework :: Django
Classifier: Framework :: Django :: 2.2
Classifier: Framework :: Django :: 3.0
Classifier: Framework :: Django :: 3.1
Classifier: Framework :: Django :: 3.2
Classifier: Framework :: Django :: 4.0
Classifier: Framework :: Django :: 4.1
Classifier: Framework :: Django :: 4.2
Classifier: Topic :: Internet :: WWW/HTTP
Classifier: Topic :: Internet :: WWW/HTTP :: Dynamic Content
Classifier: Topic :: Internet :: WWW/HTTP :: WSGI
Classifier: Topic :: Software Development :: Libraries :: Application Frameworks
Classifier: Topic :: Software Development :: Libraries :: Python Modules
Requires-Python: >=3.8
License-File: LICENSE
Requires-Dist: django-contrib-comments>=2.0
Requires-Dist: django<5,>=2.2
Requires-Dist: tzlocal>=2
Requires-Dist: bleach[css]>=5
Requires-Dist: beautifulsoup4>=4.5.3
Requires-Dist: requests>=2.1.0
Requires-Dist: requests-oauthlib>=1.3
Requires-Dist: pillow>=7
Requires-Dist: chardet>=4
Requires-Dist: pytz>=2021.1
Requires-Dist: filebrowser_safe>=1.1.1
Requires-Dist: grappelli_safe>=1.1.1
Provides-Extra: testing
Requires-Dist: pytest-django<5,>=4; extra == "testing"
Requires-Dist: pytest-cov>=2; extra == "testing"
Requires-Dist: requirements-parser>=0.11; extra == "testing"
Provides-Extra: codestyle
Requires-Dist: flake8<4,>=3; extra == "codestyle"
Requires-Dist: black==22.3.0; extra == "codestyle"
Requires-Dist: isort<6,>=5; extra == "codestyle"
Requires-Dist: pyupgrade<3,>=2; extra == "codestyle"
Dynamic: license-file
